ai_butler_sdk/__init__.py
ai_butler_sdk/apis/__init__.py
ai_butler_sdk/apis/client.py
ai_butler_sdk/celery_app/__init__.py
ai_butler_sdk/celery_app/task_example.py
ai_butler_sdk/deploy_onnx.py
ai_butler_sdk/evaluate.py
ai_butler_sdk/settings.py
ai_butler_sdk/train.py
ai_butler_sdk/utils.py
ai_butler_sdk-0.5.2.dist-info/METADATA
ai_butler_sdk-0.5.2.dist-info/WHEEL
ai_butler_sdk-0.5.2.dist-info/RECORD
