Metadata-Version: 2.1
Name: ai-butler-sdk
Version: 0.5.2
Summary: AI模型生产管理平台sdk
Author: 王凡
Author-email: wangfan@keanbang.com
Requires-Python: >=3.10,<4.0
Classifier: Programming Language :: Python :: 3
Classifier: Programming Language :: Python :: 3.10
Classifier: Programming Language :: Python :: 3.11
Classifier: Programming Language :: Python :: 3.12
Requires-Dist: celery (>=5.3.6,<6.0.0)
Requires-Dist: chardet (>=5.2.0,<6.0.0)
Requires-Dist: docker (>=7.0.0,<8.0.0)
Requires-Dist: gevent (>=24.2.1,<25.0.0)
Requires-Dist: httpx (>=0.27.0,<0.28.0)
Requires-Dist: loguru (>=0.7.2,<0.8.0)
Requires-Dist: minio (>=7.2.5,<8.0.0)
Requires-Dist: pydantic (>=2.6.4,<3.0.0)
Requires-Dist: pydantic-settings (>=2.2.1,<3.0.0)
Requires-Dist: redis (>=5.0.3,<6.0.0)
